mrshudson/__init__.py
mrshudson/lib.py
mrshudson-0.1.0a1.dist-info/LICENSE
mrshudson-0.1.0a1.dist-info/METADATA
mrshudson-0.1.0a1.dist-info/WHEEL
mrshudson-0.1.0a1.dist-info/top_level.txt
mrshudson-0.1.0a1.dist-info/RECORD
